pysplitter/__init__.py
pysplitter/_pysplitter/__init__.py
pysplitter/_pysplitter/_pysplitter.py
pysplitter-0.0.17.dist-info/LICENSE
pysplitter-0.0.17.dist-info/METADATA
pysplitter-0.0.17.dist-info/WHEEL
pysplitter-0.0.17.dist-info/top_level.txt
pysplitter-0.0.17.dist-info/RECORD
