Metadata-Version: 2.1
Name: pysplitter
Version: 0.0.17
Summary: A python package that splits large files into smaller chunks.
Home-page: https://github.com/marktodisco/pysplit
Author: Mark Todisco
License: UNKNOWN
Platform: UNKNOWN
Classifier: Programming Language :: Python :: 3
Classifier: Programming Language :: Python :: 3.7
Requires-Python: >=3.7
Requires-Dist: numpy
